{"9":["http://static.flickr.com/2320/2499313381_9ea0b339da.jpg","http://www.panthera-multimedia.nl/diashowvo/struthioniformes/stru13.jpg","http://farm4.static.flickr.com/3050/2726483745_212bfa89e3.jpg","http://farm3.static.flickr.com/2254/2461036343_8f6fd4b7f2.jpg","http://farm4.static.flickr.com/3007/2490429534_9037b8d22e.jpg?v=0","http://static.flickr.com/2386/2210305933_6373f7cef2.jpg","http://farm3.static.flickr.com/2330/2498135373_732038b15d.jpg","http://farm4.static.flickr.com/3281/3014470390_ce681a4bfd.jpg","http://tolweb.org/tree/ToLimages/ostrich_fam.250a.jpg","http://static.flickr.com/1294/695519219_03c497bbf6.jpg"],"12":["http://farm3.static.flickr.com/2276/2136863016_c1d0dcfebb.jpg","http://farm2.static.flickr.com/1052/652287581_43f03b2162.jpg","http://farm4.static.flickr.com/3183/2593768494_4b0e1961b4.jpg","http://farm4.static.flickr.com/3089/2593215467_dea76a5303.jpg","http://farm1.static.flickr.com/135/389691192_e38368f8bd.jpg","http://farm3.static.flickr.com/2330/2331901606_6ec9fc8f8c.jpg","http://farm1.static.flickr.com/101/364021532_87bf5aac19.jpg","http://farm1.static.flickr.com/168/386632183_f1e378254e.jpg","http://farm3.static.flickr.com/2218/2118168531_ccece7815c_s.jpg","http://farm3.static.flickr.com/2071/1834836172_7cf6a13356.jpg"],"24":["http://farm2.static.flickr.com/1208/1426238283_2243ac1620.jpg","http://farm3.static.flickr.com/2246/2200657761_bc6d71beff.jpg","http://farm1.static.flickr.com/26/55128165_17d0913754.jpg","http://farm4.static.flickr.com/3286/2671132060_1db12619cb.jpg","http://farm4.static.flickr.com/3086/2547240801_f2db68dfba.jpg","http://static.flickr.com/2341/2257626044_6c4d1797de.jpg","http://farm4.static.flickr.com/3023/2547256273_d8f58f4814.jpg","http://farm4.static.flickr.com/3242/2284923142_d04a762b5e.jpg?v=0","http://static.flickr.com/2395/2385387982_e69d199d66.jpg","http://static.flickr.com/3181/2548080814_8600b5db29.jpg"],"29":["http://farm4.static.flickr.com/3234/2994932075_daeb5c7196.jpg","http://www.caudata.org/forum/messages/793/23990.jpg","http://farm1.static.flickr.com/25/101019762_82796fb2a4.jpg","http://farm4.static.flickr.com/3056/2727076557_48c686769f.jpg","http://static.flickr.com/89/245890426_b6c0b17178.jpg","http://farm4.static.flickr.com/3183/2485115208_cdb1abaa87.jpg","http://blog.itachisanarea.jp/image/upa.jpg","http://farm3.static.flickr.com/2249/2152918866_ba6b23b0c2.jpg","http://www.pinkupa.com/image/pict/aquarium/diary/upa59.jpg","http://farm4.static.flickr.com/3190/2700325645_bb7daf3a26.jpg"],"36":["http://farm2.static.flickr.com/1073/1069338211_52fe2b0dd0.jpg","http://farm4.static.flickr.com/3111/2842759059_e657ed2880.jpg","http://static.flickr.com/3183/2456980428_3ea3569dbf.jpg","http://www.naturephoto-cz.com/photos/others/yellow-bellied-turtle-30381.jpg","http://farm4.static.flickr.com/3279/3032123446_9b686187c2.jpg","http://farm4.static.flickr.com/3013/2970716135_0c5aebd970.jpg","http://farm1.static.flickr.com/206/497086264_053b8a787c.jpg","http://farm4.static.flickr.com/3028/2808686182_295938c87d.jpg","http://farm2.static.flickr.com/1105/526801960_498e84c26b.jpg","http://farm2.static.flickr.com/1071/997433523_18993630dd.jpg"],"60":["http://farm1.static.flickr.com/73/181771140_21a5d720da.jpg","http://i265.photobucket.com/albums/ii204/tspuckler/nightsnake.jpg","http://farm3.static.flickr.com/2357/2299197999_88ed58d398.jpg","http://farm3.static.flickr.com/2216/2204063151_f437ee44e3.jpg","http://i30.photobucket.com/albums/c306/norcalsnakemaster/IMG_0990.jpg","http://farm4.static.flickr.com/3198/2923684339_92ab63d3b9.jpg","http://farm3.static.flickr.com/2220/2204908774_b4c5fa433f.jpg","http://i83.photobucket.com/albums/j310/GetulaHunter/Night-Snake-Spence.jpg","http://farm3.static.flickr.com/2215/2254820335_f797965e9b.jpg","http://farm2.static.flickr.com/1011/837247717_5ae41c69d5.jpg"],"101":["http://farm1.static.flickr.com/75/229703512_2551fb24e9.jpg","http://farm1.static.flickr.com/111/263069682_970498801a.jpg","http://static.flickr.com/72/229752181_a24743e4fa.jpg","http://www.indianaturewatch.net/images/album/photo/2114361606433dfaff8a3ab.jpg","http://farm1.static.flickr.com/120/250519485_32fc2e6b49.jpg","http://static.flickr.com/91/231600687_c37cc9e16e.jpg","http://static.flickr.com/15/68539829_1d6b2632ff.jpg","http://farm1.static.flickr.com/98/375803061_0c3903dd42.jpg","http://farm2.static.flickr.com/1234/1017066056_b2c0853f81.jpg","http://farm1.static.flickr.com/44/154866133_0e2449bb8d.jpg"],"102":["http://farm1.static.flickr.com/2/3060323_948eff8dfd.jpg","http://sapphires.bizhosting.com/photo/echidna.jpg","http://farm1.static.flickr.com/117/291137633_5fbe23941f.jpg","http://farm1.static.flickr.com/53/146157800_e763329e86.jpg","http://static.flickr.com/30/62430938_56abb044fd.jpg","http://farm1.static.flickr.com/122/283350630_2f923de593.jpg","http://farm1.static.flickr.com/211/495666201_2492588663.jpg","http://farm2.static.flickr.com/1229/949812387_58226e64db.jpg","http://farm3.static.flickr.com/2328/2093370906_19658f2bb3.jpg","http://farm1.static.flickr.com/48/143961395_d5b0d46020.jpg"],"136":["http://farm1.static.flickr.com/26/67776113_7a09c44ada.jpg","http://static.flickr.com/3126/2769725869_c60991fe50.jpg","http://farm1.static.flickr.com/97/271501180_b20e766ad6.jpg","http://farm1.static.flickr.com/49/171785350_24c993fb4e.jpg","http://static.flickr.com/72/176649802_0616772635.jpg","http://farm4.static.flickr.com/3259/2706761844_cdf1496770.jpg","http://farm3.static.flickr.com/2191/2127156863_05074fb204.jpg","http://farm3.static.flickr.com/2083/2524760720_a5dc1c4b7b.jpg","http://farm3.static.flickr.com/2350/2261196387_27ea097bcb.jpg","http://farm3.static.flickr.com/2228/2195195494_c5a02f8d6b.jpg"],"160":["http://farm3.static.flickr.com/2351/2214859332_ecaf0221cc.jpg","http://farm1.static.flickr.com/213/454200378_83be217afc.jpg","http://farm1.static.flickr.com/186/477107308_c9b569bc82.jpg","http://farm1.static.flickr.com/140/392214350_b56533e461.jpg","http://www.mitchellspublications.com/cs/2/os/01-image.jpg","http://farm1.static.flickr.com/201/446168240_e46b0321e0.jpg","http://farm1.static.flickr.com/139/392851148_c40eefd908.jpg","http://farm1.static.flickr.com/182/443588078_967379e812.jpg","http://farm1.static.flickr.com/30/61846231_57c5485c6c.jpg","http://farm3.static.flickr.com/2019/1935511218_4be279caa2.jpg"],"163":["http://farm3.static.flickr.com/2184/1753945846_e6ec637451.jpg","http://farm3.static.flickr.com/2047/2101803962_d018df0156.jpg","http://farm1.static.flickr.com/21/29366300_6cc55fd9ef.jpg","http://farm1.static.flickr.com/47/139358920_67294a50e5.jpg","http://farm3.static.flickr.com/2155/1584472156_6411430def.jpg","http://www.dogsk.sk/kynologia/revue/foto/bloodhound02_02b.jpg","http://www.pineycreekkennel.com/images/Christmas_Picture_woframe.JPG","http://farm2.static.flickr.com/1196/732136997_594141a10f.jpg","http://farm3.static.flickr.com/2379/2061004971_2528a89bed.jpg","http://farm1.static.flickr.com/50/140291300_5af7e966b3.jpg"],"165":["http://static.flickr.com/79/212162388_7b4f053091.jpg","http://img.dogphoria.com/web_2007_07_ab4ce870-4f6c-42af-9535-65c5f09c09f7.jpg","http://www.digitaldog.com/images/breeds/btcoon1.jpg","http://static.flickr.com/240/524206864_80bf71665b.jpg","http://i140.photobucket.com/albums/r31/wild_fire1990/HPIM0255.jpg","http://farm2.static.flickr.com/1378/923311026_bc22728260.jpg","http://farm2.static.flickr.com/1197/1348251329_2a37fbe6c2.jpg","http://farm2.static.flickr.com/1085/1349141448_12f2e04558.jpg","http://static.flickr.com/254/519226282_3490260254.jpg","http://www.dogbreedinfo.com/images11/BlackandTanCopperPuppy3.jpg"],"197":["http://farm1.static.flickr.com/48/184679418_9e599699a7.jpg","http://farm2.static.flickr.com/1054/1056923472_652eb681b2.jpg","http://www.keystonekennel.com/dogs/photo/Vinney2003NationalsWE.jpg","http://farm1.static.flickr.com/66/184679661_c8a866d90b.jpg","http://www.gentlyborn.com/g/roma/tbRoma2.jpg","http://static.flickr.com/1415/1277039617_4cb4d2b4f8.jpg","http://farm2.static.flickr.com/1382/534975620_e6e867f4a2.jpg","http://www.sustainable-gardening-tips.com/images/Mickey-for-the-website.jpg","http://static.flickr.com/1205/933415211_612508cb94.jpg","http://farm3.static.flickr.com/2387/2101635662_2e4e1848a2.jpg"],"205":["http://lh3.google.com/_ckec4bXlSO8/Rguyuq60d7I/AAAAAAAAADE/zRW3gb8EkLQ/s800/MATTIE.jpg","http://farm2.static.flickr.com/1270/561506024_b2cf2b62ef.jpg","http://farm1.static.flickr.com/182/364888994_141fbdb563.jpg","http://static.flickr.com/234/445695660_e8b3da11ec.jpg","http://farm3.static.flickr.com/2349/2197780478_99967b1c24.jpg","http://farm1.static.flickr.com/33/56990345_bc25f9a49a.jpg","http://farm1.static.flickr.com/161/402813763_19ea9813fb.jpg","http://www.celysvet.cz/fotky/flat-coated-retriever_2.jpg","http://farm1.static.flickr.com/26/345903307_c9bcc6821f.jpg","http://farm1.static.flickr.com/15/22481632_93c69c387c.jpg"],"209":["http://farm3.static.flickr.com/2261/2156484536_e5784ac102.jpg","http://farm3.static.flickr.com/2154/2145914807_4c04f48cdb.jpg","http://static.flickr.com/75/217363851_495ea6edb4.jpg","http://static.flickr.com/89/215650516_ccd22da931.jpg","http://farm2.static.flickr.com/1080/1352671096_eebdbe2723.jpg","http://farm3.static.flickr.com/2311/2221222800_e63180a8d9.jpg","http://farm2.static.flickr.com/1327/1184605507_1ac4368854.jpg","http://farm2.static.flickr.com/1410/770788439_defc88b735.jpg","http://farm3.static.flickr.com/2304/1937723833_117ae1e3fd.jpg","http://farm3.static.flickr.com/2020/1759238423_93f3847623.jpg"],"238":["http://farm1.static.flickr.com/41/81867302_5a08c665f5.jpg","http://braino.org/me/wp-content/images/0603_greaterswiss.jpg","http://static.flickr.com/41/81867343_4a1d10b7fc.jpg","http://static.flickr.com/30/47343797_24c9a15aa4.jpg","http://farm1.static.flickr.com/161/425453849_35307091fa.jpg","http://farm3.static.flickr.com/2212/2170744452_7ea2de90c8.jpg","http://farm3.static.flickr.com/2122/2169802233_3558256329.jpg","http://farm1.static.flickr.com/166/382211841_5efcadc42d.jpg","http://farm2.static.flickr.com/1129/947401050_f6bafed3b9.jpg","http://farm1.static.flickr.com/151/370145207_ab75b478b6.jpg"],"257":["http://farm3.static.flickr.com/2397/1655524063_110dcf34d3.jpg","http://www.zooclub.blister.ru/pyrenees.files/sveta-at-silva.jpg","http://farm1.static.flickr.com/180/463451883_9e61eb0c46.jpg","http://static.flickr.com/22/88933864_d385d1e0df.jpg","http://www.petoffice.co.jp/mbl/ph/zukan/dog300jpg/greatp.jpg","http://farm1.static.flickr.com/1/188179048_9042e104c6.jpg","http://www.jeffbridgman.com/5k/images/bob_earlene.jpg","http://www.milkandhoneyfarm.com/dogs/p022/Great_Pyrenees_puppies_6.jpg","http://farm1.static.flickr.com/70/214673471_5e03ce5d37.jpg","http://farm1.static.flickr.com/80/239938960_1e8b69a45f.jpg"],"266":["http://farm3.static.flickr.com/2076/1740746828_85f0da3a23.jpg","http://farm3.static.flickr.com/2206/2214638068_15be40ab94.jpg","http://farm1.static.flickr.com/108/430073361_0fbd464b20.jpg","http://www.dogbreedinfo.com/images6/TOYPOODLEPUPStwo_pups1b.jpg","http://farm1.static.flickr.com/144/357860078_27c875a060.jpg","http://farm1.static.flickr.com/238/524491550_7be9d4bc74.jpg","http://static.flickr.com/111/255370903_d1f3a4fa85.jpg","http://farm3.static.flickr.com/2069/2167716800_c7b2ae7c92.jpg","http://farm1.static.flickr.com/22/31976132_28bc0284a6.jpg","http://farm1.static.flickr.com/27/102046119_0986ebf21e.jpg"],"267":["http://static.flickr.com/177/483162177_b19ffbbc03.jpg","http://upload.wikimedia.org/wikipedia/commons/thumb/a/a6/Standard_Poodle_portrait.jpg/800px-Standard_Poodle_portrait.jpg","http://farm2.static.flickr.com/1427/1424161254_113cf754ed.jpg","http://static.flickr.com/52/149004300_28a54c01b7.jpg","http://farm3.static.flickr.com/2042/2105729531_438cce6642.jpg","http://farm1.static.flickr.com/50/163889529_8c20b017f8.jpg","http://farm2.static.flickr.com/1042/1356891002_15b2dfde06.jpg","http://farm3.static.flickr.com/2295/2175964195_749ce63034.jpg","http://farm3.static.flickr.com/2016/2024023895_b246b872fb.jpg","http://static.flickr.com/53/141492030_bb32fceb62.jpg"],"269":["http://farm1.static.flickr.com/63/159710217_811051bbcd.jpg","http://farm1.static.flickr.com/18/70862522_7e9d615b66.jpg","http://farm3.static.flickr.com/2022/2057201907_acc52dacde.jpg","http://farm3.static.flickr.com/2292/2142006205_8cdbcbde9a.jpg","http://farm2.static.flickr.com/1210/1281422273_0e16559676.jpg","http://farm3.static.flickr.com/2405/2057033501_6f6727bdde.jpg","http://farm3.static.flickr.com/2260/2179125507_24a8da4338.jpg","http://farm1.static.flickr.com/57/213557107_537942ae2b.jpg","http://farm3.static.flickr.com/2156/2030718508_191a6fd221.jpg","http://farm1.static.flickr.com/95/249966306_afaa8d55fa.jpg"],"306":["http://farm1.static.flickr.com/152/422599131_0590bd84f4.jpg","http://www.dddi.org/pacific/images/387a.jpg","http://static.flickr.com/3138/2989466102_295a1bcaf9.jpg","http://static.flickr.com/2210/2345712051_56521f8b57.jpg","http://static.flickr.com/1154/561827015_68a3369641.jpg","http://farm4.static.flickr.com/3289/3125325916_263bd31116.jpg","http://www.insectaculture.com/img/xgulysses.jpg","http://static.flickr.com/3085/2715248261_93896bc8d3.jpg","http://lh4.ggpht.com/_oBZlLnC1MDI/SFCLEq3RD9I/AAAAAAAACng/IE2gcsBbtlY/DSCF0021.JPG","http://lh4.ggpht.com/_oBZlLnC1MDI/SFCKxIhrxwI/AAAAAAAACm4/zuKm28gSmUs/DSCF0016.JPG"],"308":["http://farm1.static.flickr.com/230/481424437_32f660e92c.jpg","http://farm1.static.flickr.com/74/211330257_adebb2e399.jpg","http://static.flickr.com/95/220207234_acb56ceca7.jpg","http://farm1.static.flickr.com/191/474492335_d1f383bc1b.jpg","http://farm3.static.flickr.com/2003/2246481671_232945fb55.jpg","http://farm1.static.flickr.com/96/237011763_d5e4926556.jpg","http://static.flickr.com/2158/1559338789_4b74633351.jpg","http://farm1.static.flickr.com/191/504710878_89e7983afe.jpg","http://farm4.static.flickr.com/3043/2539104251_3f9979cb21.jpg","http://farm4.static.flickr.com/3089/2686440115_1d5a1ecd06.jpg"],"319":["http://lh3.ggpht.com/_pJx1vx1o9wE/SDnE6FKtBDI/AAAAAAAAAMQ/IfArWZ1h8sk/CABALLO+DEL+DIABLO.JPG","http://aminus3.s3.amazonaws.com/image/g0002/u00001964/i00051505/bf7d7c3123cfbf993ea9f8c1b1bd9817_large.jpg","http://static.flickr.com/1111/1259481811_011fa60427.jpg","http://static.flickr.com/1266/1064594116_5790d60881.jpg","http://myninjaplease.com/wp-content/uploads/2007/09/rusty_the_dragonfly.jpg","http://static.flickr.com/1101/1449512265_5e3b355480.jpg","http://static.flickr.com/2088/1521116333_c671b48873.jpg","http://static.flickr.com/1022/1318141589_f5df8d2a8f.jpg","http://farm3.static.flickr.com/2233/2254094691_504bfa9554.jpg","http://static.flickr.com/3164/3080134669_a8eae46a4c.jpg"],"333":["http://farm1.static.flickr.com/107/258312871_8b38bbce19.jpg","http://farm1.static.flickr.com/42/113798145_b2fc6d37e8.jpg","http://farm2.static.flickr.com/1283/577358931_dccb54a502.jpg","http://farm1.static.flickr.com/144/369246062_8e0578349f.jpg","http://farm2.static.flickr.com/1368/539913878_4bb4c616d8.jpg","http://farm1.static.flickr.com/172/370912814_918d7072ca.jpg","http://static.flickr.com/1013/1434009672_db46cb82b3.jpg","http://farm2.static.flickr.com/1021/1046667069_403c347c9c.jpg","http://farm1.static.flickr.com/219/502489195_826cd258cf.jpg","http://farm1.static.flickr.com/21/91129400_34ac5f1b7e.jpg"],"337":["http://farm3.static.flickr.com/2365/1767674476_54f55cb247.jpg","http://www.canada-photos.com/data/homepage/18/beaver-animal_391.jpg","http://farm2.static.flickr.com/1012/753174582_cb586cfa51.jpg","http://www.torontozoo.com/images/animals/Beaver.jpg","http://farm1.static.flickr.com/28/53145661_a7442e3e70.jpg","http://www.kidsfarm.com/images/beavers/babybeaver_l.jpg","http://www.budknawwood.com/Aplodontia_files/IM003477.jpg","http://www.conciencia-animal.cl/paginas/noticias/fotos/castor.jpeg","http://www.cbc.ca/gfx/images/news/photos/2006/08/28/bc-beaver.jpg","http://farm1.static.flickr.com/54/156674968_e46613f4d1.jpg"],"377":["http://farm1.static.flickr.com/88/226218785_02dacac2a5.jpg","http://farm2.static.flickr.com/1234/627517810_51d5e8cefd.jpg","http://farm1.static.flickr.com/161/347828297_a68f0ce56a.jpg","http://static.flickr.com/2398/1543499532_f2dc185ca9.jpg","http://static.flickr.com/2317/1680215578_88af8f2625.jpg","http://farm1.static.flickr.com/44/190221669_47e9a65ffd.jpg","http://farm1.static.flickr.com/178/471167149_582d523a10.jpg","http://upload.wikimedia.org/wikipedia/commons/thumb/9/9d/Marmoset_copy.jpg/200px-Marmoset_copy.jpg","http://farm1.static.flickr.com/27/60132777_8cf993e93a.jpg","http://farm1.static.flickr.com/67/163773882_27da36626b.jpg"],"395":["http://i259.photobucket.com/albums/hh293/Ibb1gdaddy2/GatorGar4-13-089.jpg","http://farm3.static.flickr.com/2024/2505972011_a6360cacfd.jpg","http://www.woodlandsonline.com/images/nltimage/AlligatorGarFish.jpg","http://farm3.static.flickr.com/2346/2267449026_61a3d41dd6.jpg?v=0","http://farm1.static.flickr.com/11/14865969_4f1eb5a56d.jpg","http://farm4.static.flickr.com/3002/2792590683_e59a8b44c0.jpg?v=0","http://farm1.static.flickr.com/11/12716099_2c387b5f1e.jpg","http://farm3.static.flickr.com/2366/1911735053_b27c43c119.jpg","http://farm1.static.flickr.com/184/468821864_96270ac7ae.jpg","http://static.flickr.com/1234/527145709_6ad0829643.jpg"],"440":["http://farm1.static.flickr.com/118/303536732_0f6ffbebe2.jpg","http://farm3.static.flickr.com/2318/2236846854_1099656f36.jpg","http://farm4.static.flickr.com/3177/2588496220_4f47735b53.jpg","http://farm3.static.flickr.com/2197/2495301335_d1da2c6ff2.jpg","http://farm1.static.flickr.com/55/360500196_80ed9cadeb.jpg","http://farm4.static.flickr.com/3235/3070809433_f03e0f125c.jpg","http://farm1.static.flickr.com/116/302393840_d2ae58227a.jpg","http://farm4.static.flickr.com/3265/3183677923_7642d8e2e1.jpg","http://farm4.static.flickr.com/3508/3190054689_2ffeae2d06.jpg","http://farm4.static.flickr.com/3277/2330267081_091047a2c5.jpg"],"491":["http://farm1.static.flickr.com/51/151805053_4c21117e00.jpg","http://www.euro-shopping.info/catalog/images/mjcs2138.jpg","http://farm2.static.flickr.com/1291/1145549320_b3ac9895ea.jpg","http://img.epinions.com/images/opti/97/06/kifmBoys_PlaysetsToolsReal_Sounds_Power_Tool__Chain_Saw-resized200.jpg","http://www.deere.com/en_US/ProductCatalog/HO/media/images/product/cs40le_404139_1col.jpg","http://farm1.static.flickr.com/113/299851341_b28265dc75.jpg","http://farm1.static.flickr.com/79/220882097_4ab624ed4b.jpg","http://www.motogreen.com/images/925Motosega.jpg","http://farm1.static.flickr.com/91/419084140_1d3d04a519.jpg","http://farm3.static.flickr.com/2290/2096065079_5eb4ebd659.jpg"],"494":["http://farm3.static.flickr.com/2190/2065124177_167caff936.jpg","http://farm3.static.flickr.com/2244/1917396665_8fd186b939.jpg","http://static.flickr.com/2017/2302865718_f03b248d38.jpg","http://www.toteunlimited.com/store/image.php?productid=23053","http://sansenya.com/photos/myochin.jpg","http://www.musicinventions.org/meadowview/chimes.jpg","http://farm1.static.flickr.com/77/172851831_22e7938554.jpg","http://static.flickr.com/161/341948827_58ea8d6ac9.jpg","http://www.yamaha.com/yamahavgn/Images/BandOrchestra/Product/Main/chimes_585_main.jpg","http://farm1.static.flickr.com/223/444244452_35c004e2ea.jpg"],"500":["http://farm4.static.flickr.com/3083/3139208288_4020e26ca8.jpg","http://farm2.static.flickr.com/1073/1405846078_89f9c81cd7.jpg","http://farm3.static.flickr.com/2137/1675554621_f2e377d46c.jpg","http://farm4.static.flickr.com/3056/3014042161_6802bd93fe.jpg","http://farm1.static.flickr.com/57/201473335_0cbb276d51.jpg","http://farm1.static.flickr.com/107/250833563_4ea048b97b.jpg","http://farm1.static.flickr.com/28/56910815_2983703f95.jpg","http://farm3.static.flickr.com/2282/2411129737_f7cc2ababc.jpg","http://farm4.static.flickr.com/3322/3177687820_f691079bec.jpg","http://farm4.static.flickr.com/3079/3173217219_98f33512d1.jpg"],"552":["http://farm2.static.flickr.com/1101/1450042505_aaea811390.jpg","http://farm4.static.flickr.com/3463/3248994391_d1dbce2371.jpg","http://farm1.static.flickr.com/14/15273839_f18869a2b1.jpg","http://farm4.static.flickr.com/3571/3301927723_e900b98a08.jpg","http://farm1.static.flickr.com/180/402614862_94c7076559.jpg","http://farm1.static.flickr.com/171/416084848_3fe57f2ccd.jpg","http://farm2.static.flickr.com/1053/1433035737_3fece8f370.jpg","http://farm4.static.flickr.com/3595/3331153302_50cb8d6902.jpg","http://farm4.static.flickr.com/3631/3302845020_8cae80e224.jpg","http://farm4.static.flickr.com/3223/2593564029_9d2f0e1130.jpg"],"574":["http://farm3.static.flickr.com/2191/2028104306_5417a7187e.jpg","http://farm4.static.flickr.com/3059/2575113413_d395910701.jpg","http://farm1.static.flickr.com/98/229596067_5d1309858d.jpg","http://farm4.static.flickr.com/3122/2575986870_24945ab6c9.jpg","http://farm3.static.flickr.com/2134/1717526132_1b968a4b87.jpg","http://farm4.static.flickr.com/3560/3388602293_0bfd7435e7.jpg","http://farm3.static.flickr.com/2246/2509144576_e9f4d30594.jpg","http://farm3.static.flickr.com/2162/2151726534_53a0e04c63.jpg","http://farm1.static.flickr.com/22/28715602_9c029c5529.jpg","http://farm2.static.flickr.com/1401/1430508432_4bbe102e8f.jpg"],"605":["http://img1.pconline.com.cn/pconline/0707/13/1057456_touchscreen-ipod-rumor-230.jpg","http://farm4.static.flickr.com/3178/3056624185_11d10edced.jpg","http://farm4.static.flickr.com/3163/2436888830_c5d3d35716.jpg","http://farm1.static.flickr.com/29/42692294_270a9cfd1c.jpg","http://farm3.static.flickr.com/2019/2037711703_caee3901d5.jpg","http://farm1.static.flickr.com/169/413799006_7c7242acb2.jpg","http://farm4.static.flickr.com/3047/2843740997_53a3b7b286.jpg","http://static.flickr.com/50/148367176_27307567cf.jpg","http://farm4.static.flickr.com/3510/3249882747_9a219795f1.jpg","http://farm4.static.flickr.com/3187/2406742788_6abc7d32e3.jpg"],"606":["http://farm2.static.flickr.com/1081/1346986055_a1b5f9e3cc.jpg","http://img.2dehands.be/f/normal/24109978-antiek-strijkijzer.jpg","http://pic.nipic.com/2007-08-19/2007819174713132_2.jpg","http://farm2.static.flickr.com/1123/687635879_065923f0e6.jpg","http://img.kelkoo.com/CS/large/703/120/008613980794953098550928641978914120703.jpg","http://i02.c.aliimg.com/img/offer/19/27/28/49/7/192728497.search.jpg","http://farm3.static.flickr.com/2079/2438351424_87705d934a.jpg","http://farm4.static.flickr.com/3003/2338719385_a03409457e.jpg","http://img3.dangdang.com/image/193/20193904_1_thumb300.jpg","http://img3.dangdang.com/image/084/20084270_1_thumb300.jpg"],"610":["http://farm4.static.flickr.com/3595/3376873527_976ec8cac3.jpg","http://farm1.static.flickr.com/122/280590579_360f63cc02.jpg","http://farm4.static.flickr.com/3309/3346545824_e8bff7f419.jpg","http://farm4.static.flickr.com/3555/3384297141_7f302c7edf.jpg","http://farm4.static.flickr.com/3571/3293130171_cab5a044fb.jpg","http://farm4.static.flickr.com/3187/2385484530_39d2343a7f.jpg","http://farm4.static.flickr.com/3304/3191826422_ae70502896.jpg","http://farm4.static.flickr.com/3472/3273935093_1bb9bfb810.jpg","http://www.serifast.it/ebay/design/D055-110M-OLI.jpg","http://farm1.static.flickr.com/55/115063764_c2f1821015.jpg"],"628":["http://farm3.static.flickr.com/2335/2425680080_3c15f019ec.jpg","http://farm4.static.flickr.com/3074/2701145785_1be5a2a036.jpg","http://farm4.static.flickr.com/3072/2570265468_1d0e129523.jpg","http://farm3.static.flickr.com/2320/2069825992_91bcc05385.jpg","http://farm2.static.flickr.com/1388/1080056011_336c44b914.jpg","http://farm1.static.flickr.com/37/119228249_df2d574971.jpg","http://farm3.static.flickr.com/2393/2280239825_951d1daf7f.jpg","http://farm3.static.flickr.com/2081/2069823792_12b2583a72.jpg","http://farm3.static.flickr.com/2415/2180332764_2b4b822bc2.jpg","http://farm4.static.flickr.com/3029/2521095729_1c747a9fa6.jpg"],"630":["http://slimages.macys.com/is/image/MCY/products/6/optimized/484246_fpx.tif?bgc=255,255,255&wid=167&qlt=90,0&layer=comp&op_sharpen=0&resMode=bicub&op_usm=0.7,1.0,0.5,0&fmt=jpeg","http://i4.ebayimg.com/06/i/001/37/4b/df96_1_sbl.JPG","http://farm4.static.flickr.com/3097/2710815697_642d7b1d67.jpg","http://www.zappos.com/images/083/7129083/62965-d.jpg","http://i21.ebayimg.com/03/i/001/19/d0/6cb3_1.JPG","http://www.acevintage.com/images/7178c.jpg","http://farm1.static.flickr.com/48/127185191_22d7d88e4e.jpg","http://images.productserve.com/preview/649/318479.jpg","http://www.zappos.com/images/644/7128644/62070-d.jpg","http://farm4.static.flickr.com/3262/2762600567_cf2e485468.jpg"],"637":["http://farm3.static.flickr.com/2333/2147033557_76ca703a56.jpg","http://farm4.static.flickr.com/3137/2994735103_f49c5eb92e.jpg","http://farm4.static.flickr.com/3321/3172140971_d1e289e8b9.jpg","http://farm4.static.flickr.com/3178/2936992441_09226c2275.jpg","http://farm3.static.flickr.com/2418/2500045708_2828808ce9.jpg","http://farm4.static.flickr.com/3105/2627805697_c8daf00c1c.jpg","http://farm4.static.flickr.com/3201/2430708119_a598d1c58d.jpg","http://farm4.static.flickr.com/3370/3317238455_f13089bb5e.jpg","http://farm4.static.flickr.com/3351/3301387923_f4fcf75100.jpg","http://farm4.static.flickr.com/3641/3334815142_8b3e3d563b.jpg"],"646":["http://farm3.static.flickr.com/2313/2387405248_717a877319.jpg","http://farm1.static.flickr.com/69/191461527_613d6200a3.jpg","http://farm4.static.flickr.com/3274/2886833023_05ac2e7939.jpg","http://static.flickr.com/132/407448517_241e627747.jpg","http://www.derkleinegarten.de/800_lexikon/804_hecken/bilder/rasen_labyrinth.JPG","http://farm1.static.flickr.com/110/313578483_e86722277c.jpg","http://farm3.static.flickr.com/2001/2641205638_d129c52826.jpg","http://farm3.static.flickr.com/2366/2523130540_0441907447.jpg","http://farm4.static.flickr.com/3120/2901054175_2b2c33b601.jpg","http://farm4.static.flickr.com/3660/3309979131_24007a1d33.jpg"],"647":["http://farm2.static.flickr.com/1422/1087906181_0d71073d8f.jpg","http://farm3.static.flickr.com/2082/2242644802_14eb5d0000.jpg","http://farm4.static.flickr.com/3358/3253462787_2d39c8e782.jpg","http://farm1.static.flickr.com/224/520925363_e38e47c77d.jpg","http://farm4.static.flickr.com/3154/3058686527_9e2e2dc7f1.jpg","http://i04.c.aliimg.com/img/offer/20/41/33/47/4/204133474","http://farm4.static.flickr.com/3033/3444977760_db5b235b23.jpg","http://farm4.static.flickr.com/3449/3238571697_5451f64e78.jpg","http://farm4.static.flickr.com/3134/2285044929_37807df409.jpg","http://farm1.static.flickr.com/153/344977288_55fe000276.jpg"],"655":["http://farm4.static.flickr.com/3026/2862556149_e0b3293acb.jpg","http://farm4.static.flickr.com/3333/3438169194_ab9e67ca87.jpg","http://farm4.static.flickr.com/3546/3518329460_177b3c7645.jpg","http://farm1.static.flickr.com/132/388134339_e809d008aa.jpg","http://farm4.static.flickr.com/3620/3499878933_0a2bb71b76.jpg","http://farm4.static.flickr.com/3556/3419236917_e3182e4108.jpg","http://debenhams.scene7.com/is/image/Debenhams/20090123_103010830560?$SearchResults$","http://farm3.static.flickr.com/2385/2227020363_96cf72e107.jpg","http://farm4.static.flickr.com/3268/2340048848_96eba0cdd7.jpg","http://farm3.static.flickr.com/2206/2660831584_c91ba0fca0.jpg"],"661":["http://farm1.static.flickr.com/43/75294492_061467d229.jpg","http://autostadt.hornecker-online.de/zeithaus_ford_t_model_460.jpg","http://farm4.static.flickr.com/3129/2705074494_cc81cafbf8.jpg","http://farm4.static.flickr.com/3203/2704940281_064b0e71f1.jpg","http://farm1.static.flickr.com/209/491772266_cf0aaebe73.jpg","http://farm1.static.flickr.com/54/141432675_276951a07b.jpg","http://farm4.static.flickr.com/3178/2711517267_3f00179010.jpg","http://monsterblog.lzsportsource.com/images/fanphotogallery/mckram/hogg/ModelT.jpg","http://farm1.static.flickr.com/81/241447627_9970fc814d.jpg","http://farm1.static.flickr.com/46/146861612_7b74713e4d.jpg"],"678":["http://www.automobilsport.com/upload/cars-tuning-234/bmw-motorrad-neck-brake-system-1.jpg","http://static.flickr.com/1406/1386047544_6229a11d54.jpg","http://www.1000ps.at/magazin/mexx/nb6.jpg","http://static.flickr.com/2369/2417596059_1536b597d4.jpg","http://i141.photobucket.com/albums/r46/Motorbiker_photos/NewsPics/oldNewsPics2/KTM-Leatt-Neck-Brace.jpg","http://static.flickr.com/3258/2648201621_29929f9eae.jpg","http://images.usatoday.com/sports/motor/_photos/2001-02-19-inside-hans.jpg","http://static.flickr.com/120/287854489_850847c21d.jpg","http://i264.photobucket.com/albums/ii161/d55555688/P8300099.jpg","http://www.crf450x.net/wp-content/uploads/2007/02/leatt_brace.jpg"],"680":["http://farm4.static.flickr.com/3589/3402636911_d95b7914ce.jpg","http://farm2.static.flickr.com/1032/1290015677_5dfa817c6b.jpg","http://www.thisoldtoy.com/fisher-price/dept-2-dolls-stuffed-animals/d-puffalump-purrtender/1-pics/fpt19700-puff-bottle.JPG","http://www.equusite.com/articles/stories/images/orphanMaddieBottle.jpg","http://farm4.static.flickr.com/3440/3370697179_d59732b7a1.jpg","http://1.bp.blogspot.com/_EjRN5esJmyA/SNgSXDteoDI/AAAAAAAABt0/BnGItGU3fek/s400/P9230005a.jpg","http://www.loperland.com/images/uploads/podee_1.jpg","http://farm1.static.flickr.com/196/478322869_64c08e4539.jpg","http://farm4.static.flickr.com/3100/3421721915_54e3b40d7b.jpg","http://farm2.static.flickr.com/1312/1317472568_2182d00eab.jpg"],"704":["http://farm1.static.flickr.com/73/211446732_d661bca38b.jpg","http://farm4.static.flickr.com/3182/2963285909_8d278212ac.jpg","http://farm4.static.flickr.com/3037/2916948468_38c6df0f68.jpg","http://farm4.static.flickr.com/3199/2980431916_93e62ca776.jpg","http://farm1.static.flickr.com/4/9688688_797a9d8bf8.jpg","http://farm1.static.flickr.com/165/417740432_2075e35633.jpg","http://farm4.static.flickr.com/3005/2375172960_46641a008c.jpg","http://farm1.static.flickr.com/39/102406346_4231cedcb9.jpg","http://farm1.static.flickr.com/184/437934502_4d3aa83cb8.jpg","http://farm4.static.flickr.com/3263/2854134758_93f0194112.jpg"],"705":["http://farm4.static.flickr.com/3203/2663016803_e8ee796354.jpg","http://farm1.static.flickr.com/121/288804703_3102990848.jpg","http://www.e-works.net.cn/images/128098464152343750.jpg","http://classicrail.com/ncry/cars/2945.JPEG","http://farm1.static.flickr.com/70/153432831_6e2f564e7a.jpg","http://farm4.static.flickr.com/3188/2682643827_550d002b0f.jpg","http://www.alabamarailfan.com/jpegs/csx_994302b.jpg","http://farm3.static.flickr.com/2057/2314223972_b13748d032.jpg","http://farm4.static.flickr.com/3022/2570797053_1df315936f.jpg","http://farm1.static.flickr.com/209/511446407_e538a6c1dd.jpg"],"712":["http://www.caigou.com.cn/upfile/pro/2007/10/17/200710174902654827.gif","http://www.whoi.edu/cms/images/graphics-SSF_Lauren_Watka-_TOM6613_84082.jpg","http://www.esa.int/images/fotos7-1-05A_M.jpg","http://farm4.static.flickr.com/3197/3106359511_069926d346.jpg","http://farm2.static.flickr.com/1324/1237859472_6532d81d8c.jpg","http://farm4.static.flickr.com/3372/3422368734_7905ed62da.jpg","http://i100.twenga.com/10/tp/52/22/6351628424177155222.png","http://farm1.static.flickr.com/75/204198925_0c9795e079.jpg","http://farm3.static.flickr.com/2022/1544666072_e2430b2291.jpg","http://farm1.static.flickr.com/4/8586626_c41678ce81.jpg"],"718":["http://farm4.static.flickr.com/3027/2900624538_abb2bd460c.jpg","http://farm4.static.flickr.com/3192/3058546427_4981a5ddeb.jpg","http://static.flickr.com/2069/2079906630_acea92d82b.jpg","http://www.iowadot.gov/bridge/images/prairiebridgepier.jpg","http://static.flickr.com/1126/1449848786_37f51cdb63.jpg","http://farm1.static.flickr.com/28/50501662_faf28f7c11.jpg","http://graphics8.nytimes.com/packages/images/photo/2008/06/26/20080626FALL/23848007.JPG","http://static.flickr.com/213/499149213_ec53eebabc.jpg","http://www.rebuildingi93.com/_resources/images/photos/thumbnails/crossstreet/Cross-Street-Median-Pier.jpg","http://farm3.static.flickr.com/2075/2423462078_ac63ea2bae.jpg"],"748":["http://farm4.static.flickr.com/3272/2962077709_435776c4db.jpg","http://farm4.static.flickr.com/3056/2570301999_9dd0f18cdd.jpg","http://farm4.static.flickr.com/3243/3131023281_bb3c3d6f07.jpg","http://farm1.static.flickr.com/206/524639371_58123a46b6.jpg","http://farm3.static.flickr.com/2169/1612539771_29a560e7b0.jpg","http://farm1.static.flickr.com/53/176210747_16c78ee375.jpg","http://farm2.static.flickr.com/1068/1347933598_ed20d264c9.jpg","http://2.bp.blogspot.com/_x7E4C6YGXPY/SWX-qRUFP8I/AAAAAAAAA00/h2s2RKiXSro/s400/vilten+portemonnee.jpg","http://farm4.static.flickr.com/3259/3101660940_da4b5b5b26.jpg","http://www.buysellcommunity.com/uploads/120607/ww1/vlujnxhmectl.jpg"],"770":["http://farm4.static.flickr.com/3146/2341943045_3818ef0d38.jpg","http://farm4.static.flickr.com/3249/2903264957_b95003a884.jpg","http://farm4.static.flickr.com/3182/2321917816_d1617ca85e.jpg","http://farm4.static.flickr.com/3493/3180086923_0ed3720f18.jpg","http://farm4.static.flickr.com/3165/2938057036_5c55ec352f.jpg","http://farm1.static.flickr.com/69/194433768_bc000d69df.jpg","http://farm1.static.flickr.com/238/517789955_94891ec420.jpg","http://farm3.static.flickr.com/2076/2375482303_2a7d41290b.jpg","http://i00.c.aliimg.com/img/offer/25/94/31/31/6/259431316-1","http://farm4.static.flickr.com/3418/3185680798_3928cfc42a.jpg"],"780":["http://farm4.static.flickr.com/3194/2297473898_399be3df6d.jpg","http://farm1.static.flickr.com/73/204392134_b60d83e009.jpg","http://farm2.static.flickr.com/1273/542354762_36ca434e8e.jpg","http://farm1.static.flickr.com/115/278162227_638661781c.jpg","http://farm2.static.flickr.com/1297/1341628062_cab3ce3fee.jpg","http://farm1.static.flickr.com/86/235462547_4e2196ec7a.jpg","http://farm1.static.flickr.com/56/138773357_1a7bb51d11.jpg","http://farm1.static.flickr.com/173/469147985_eb06a033dd.jpg","http://farm1.static.flickr.com/183/413092707_d73f45fbf3.jpg","http://farm2.static.flickr.com/1161/686309379_01a47ce6e6.jpg"],"782":["http://www.barcodebonanza.com/images/mfg/crt.jpg","http://img.2dehands.be/f/view/40809850-tft-15-scherm-met-defect.jpg","http://farm4.static.flickr.com/3005/2684817970_422d0f576c.jpg","http://farm2.static.flickr.com/1064/1254779407_f26be62d23.jpg","http://farm4.static.flickr.com/3101/2684005305_f59a818979.jpg","http://farm1.static.flickr.com/80/229425032_c73d26fe13.jpg","http://farm1.static.flickr.com/169/464557347_75e34a2548.jpg","http://www.avadirect.com/image.asp?name=VIEWSONIC_E90F.gif","http://static.flickr.com/3131/2684005107_0044d938e4.jpg","http://img.product.pchome.net/market/photo/2006/05/24/17744.jpg"],"801":["http://farm1.static.flickr.com/209/503722625_a54dbcb951.jpg","http://farm4.static.flickr.com/3120/2615182925_977087afd9.jpg","http://farm4.static.flickr.com/3112/2443105337_d567548239.jpg","http://farm1.static.flickr.com/219/471786008_5dcd4faaf8.jpg","http://farm4.static.flickr.com/3066/2635531600_86c6e3aaf8.jpg","http://farm1.static.flickr.com/130/394111482_5d5b8cad3c.jpg","http://farm1.static.flickr.com/147/336723812_15e9e2750e.jpg","http://www.catchtravels.com/Images/CUR_Dolphin_snorkel.jpeg","http://farm1.static.flickr.com/33/103569339_25022a5e0a.jpg","http://farm1.static.flickr.com/157/389939452_067291aa5e.jpg"],"834":["http://farm4.static.flickr.com/3565/3468951010_49ecf6ab01.jpg","http://farm4.static.flickr.com/3273/2916983292_0051e26898.jpg","http://farm2.static.flickr.com/1174/1390149926_eed92469c3.jpg","http://farm1.static.flickr.com/36/113698309_aca391ee3c.jpg","http://farm4.static.flickr.com/3137/2309100107_072877b562.jpg","http://farm4.static.flickr.com/3656/3381999244_931898a2ce.jpg","http://farm1.static.flickr.com/215/507039456_0bdab4476d.jpg","http://farm4.static.flickr.com/3152/2574314790_869d33899b.jpg","http://farm4.static.flickr.com/3046/2981138617_eae180e702.jpg","http://farm4.static.flickr.com/3327/3288510721_ec541da7c2.jpg"],"901":["http://www.jdcollectorspage.com/images/Landlord2.jpg","http://bp3.blogger.com/_8sMNdo_onYs/R7rn235ITnI/AAAAAAAABR8/2rKiN0PpLHQ/s400/brown-jug.jpg","http://images.worthpoint.com/files/pb/tn/526/1845/818.jpg","http://lh3.ggpht.com/_njaAGZjbgbM/SH4qasQCmaI/AAAAAAAAALs/hoXZc2m4AKA/P6230162.JPG","http://www.jdcollectorspage.com/images/Spoon_jug.jpg","http://www.jdcollectorspage.com/images/Gr_jug2.jpg","http://ny-image0.etsy.com/il_430xN.62080992.jpg","http://www.ne.jp/asahi/miniature/smallworld/image/Michter5L.jpg","http://www.bottlebooks.com/questions/Dec2003/Cello%20Whiskey%202a_2d03.jpg","http://www.bottlebooks.com/questions/Sept2006/Jug%207..jpg"],"915":["http://www.paranormalparanormal.com/images/yurt1.jpg","http://farm4.static.flickr.com/3131/2741872427_a150dd4db7.jpg","http://farm4.static.flickr.com/3006/2899701742_1a067d06a6.jpg","http://farm1.static.flickr.com/18/22750174_a1540bf5d0.jpg","http://farm4.static.flickr.com/3131/3105782183_db0a8b213d.jpg","http://farm1.static.flickr.com/116/368531012_33e1f4c443.jpg","http://farm1.static.flickr.com/63/186189960_de870ab0be.jpg","http://farm1.static.flickr.com/5/4797924_9eccea60d7.jpg","http://farm4.static.flickr.com/3160/2332528000_ab9dd60e1e.jpg","http://farm4.static.flickr.com/3034/2946406314_ef68ae523a.jpg"],"922":["http://farm4.static.flickr.com/3383/3420927629_2bf92196d8.jpg","http://farm1.static.flickr.com/40/79543193_207d6219f4.jpg","http://farm4.static.flickr.com/3049/2745241508_323cf2baab.jpg","http://farm4.static.flickr.com/3542/3650125333_e8efd5631c.jpg","http://farm4.static.flickr.com/3128/2378315070_98e3dd0cb0.jpg","http://farm4.static.flickr.com/3297/3559568420_c5b3cd0bb1.jpg","http://farm3.static.flickr.com/2608/3771462669_a1b024e45f.jpg","http://farm2.static.flickr.com/1168/1056258828_29b90aa552.jpg","http://farm3.static.flickr.com/2032/2506399801_f6b224e67d.jpg","http://farm1.static.flickr.com/143/336874907_6b99df1f62.jpg"],"927":["http://farm4.static.flickr.com/3045/2760157100_270b1805b4.jpg","http://farm1.static.flickr.com/165/346650027_6dd3c88835.jpg","http://farm4.static.flickr.com/3049/3074657955_370727004b.jpg","http://farm1.static.flickr.com/130/321504257_08b999d25a.jpg","http://farm4.static.flickr.com/3254/3932755454_711c3f85a5.jpg","http://farm2.static.flickr.com/1227/750924234_b006520d8f.jpg","http://farm1.static.flickr.com/188/408796126_39e0761eae.jpg","http://farm1.static.flickr.com/41/110099583_e63cb6bff4.jpg","http://farm3.static.flickr.com/2528/4205050831_8dea876e00.jpg","http://farm4.static.flickr.com/3261/3148299559_3fb72a4f59.jpg"],"938":["http://farm4.static.flickr.com/3172/3077475780_3e73d47e42.jpg","http://farm1.static.flickr.com/149/400270224_d72a8913c6.jpg","http://farm3.static.flickr.com/2345/2438564316_bb7083dccc.jpg","http://farm1.static.flickr.com/131/354606010_66a052e87c.jpg","http://static.flickr.com/2052/2284014116_bdfe923e64.jpg","http://static.flickr.com/89/249313128_ce9f40457a.jpg","http://farm4.static.flickr.com/3207/2691057640_dd3b1e1c29.jpg","http://acookinglife.typepad.com/a_cooking_life/images/2007/06/17/cauliflower.jpg","http://static.flickr.com/117/289600493_9efaf76798.jpg","http://farm4.static.flickr.com/3046/2634367569_c31d908771.jpg"],"942":["http://farm4.static.flickr.com/3292/2892295387_49fc98e6b9.jpg","http://farm4.static.flickr.com/3057/2978162894_1dbb47bb33.jpg","http://farm1.static.flickr.com/29/63410248_6c6ea5d797.jpg","http://farm4.static.flickr.com/3063/3043979045_2efe89a2e3.jpg","http://farm4.static.flickr.com/3198/3108200793_398d6a6375.jpg","http://farm3.static.flickr.com/2225/2426292986_75b2216178.jpg","http://farm4.static.flickr.com/3007/2943958702_31b5bed24c.jpg","http://farm4.static.flickr.com/3232/2940673628_8608d34a19.jpg","http://farm3.static.flickr.com/2039/1989844095_b7bae7e2e1.jpg","http://farm4.static.flickr.com/3230/3016612806_1a14eef3fd.jpg"],"976":["http://static.flickr.com/42/104935951_6c6dd6373a.jpg","http://static.flickr.com/159/373175064_0f70dc58fe.jpg","http://static.flickr.com/44/108864431_fefd24053b.jpg","http://www.theodora.com/wfb/photos/lebanon/ras_ech-chaqaa_promontory_batroun_lebanon_photo_gov.jpg","http://www.archaeoastronomy.it/santa%20giulia2.JPG","http://www.geograph.org.uk/photos/00/10/001014_62c55695.jpg","http://lh3.ggpht.com/_GJ5sp63U4_w/R71TzLrl0gI/AAAAAAAAAY8/iL8K8wN_nsc/punta+del+bacio.jpg","http://www.underwater.com.au/images/location/wilsons_promontory_2.jpg","http://www.americansouthwest.net/utah/photographs700/deadhorse3.jpg","http://static.flickr.com/3177/2580572632_41dfb4d420.jpg"],"994":["http://static.flickr.com/2094/1610114514_5395f7825b.jpg","http://static.flickr.com/3180/3026443627_f10778c059.jpg","http://static.flickr.com/29/50411404_1ad715d25c.jpg","http://farm3.static.flickr.com/2035/2244812119_c6ec7f7fb8.jpg","http://www.jacquidracup.co.uk/images/fungi/tf5.jpg","http://static.flickr.com/2161/2117069109_dd7f21a720.jpg","http://farm4.static.flickr.com/3071/3037884256_8920ee8f5f.jpg","http://farm2.static.flickr.com/1286/817439097_175f5dbd1c.jpg","http://www.bulletin.uwaterloo.ca/images/2008/0917fungus.jpg","http://www.mykoweb.com/CAF/photos/large/Phallus_hadriani(mgw-05).jpg"],"998":["http://farm2.static.flickr.com/1009/1301791936_4d2137401a.jpg","http://farm2.static.flickr.com/1214/1115486921_792f36099d.jpg","http://farm2.static.flickr.com/1208/1469659790_aaf48fa39d.jpg","http://farm4.static.flickr.com/3250/2707649748_22c7051323.jpg","http://farm3.static.flickr.com/2393/2730383948_25037d2a0e.jpg","http://farm1.static.flickr.com/224/518773535_e69e523674.jpg","http://farm4.static.flickr.com/3135/2700127050_1063a6d7af.jpg","http://farm4.static.flickr.com/3114/2756505935_7e13726fde.jpg","http://ag.arizona.edu/crop/images/database/other/images/Imgf8088.jpg","http://farm4.static.flickr.com/3259/2755365894_67925c49f9.jpg"]}